{
  "collectionName": "components_material_item",
  "info": {
    "icon": "receipt",
    "description": "",
    "displayName": "Item"
  },
  "options": {},
  "attributes": {
    "file": {
      "type": "media",
      "allowedTypes": [
        "files",
        "images",
        "videos"
      ],
      "multiple": false,
      "required": false
    },
    "description": {
      "type": "customField",
      "options": {
        "preset": "markdown"
      },
      "customField": "plugin::ckeditor5.CKEditor"
    },
    "external_link": {
      "type": "string"
    },
    "name": {
      "type": "string"
    }
  }
}
